LICENSE
README.md
setup.py
multiPrime/__init__.py
multiPrime.egg-info/PKG-INFO
multiPrime.egg-info/SOURCES.txt
multiPrime.egg-info/dependency_links.txt
multiPrime.egg-info/entry_points.txt
multiPrime.egg-info/top_level.txt
src/_version.py
src/main.py
src/src.py
src/utils.py