Metadata-Version: 2.1
Name: multiPrime
Version: 2.4.7
License: MIT
Requires-Python: >=3.6
License-File: LICENSE
